main.py
test_deployment-1.0.4.dist-info/METADATA
test_deployment-1.0.4.dist-info/WHEEL
test_deployment-1.0.4.dist-info/top_level.txt
test_deployment-1.0.4.dist-info/RECORD
