Metadata-Version: 2.1
Name: test-deployment
Version: 1.0.4
Summary: test deployment
Author: test user
Author-email: manishpary@gmail.com
